lif_reader/__init__.py
lif_reader/lif_reader.py
lif_reader/graph/__init__.py
lif_reader/graph/graph_renderer.py
lif_reader/graph/lif_graph.py
lif_reader/models/__init__.py
lif_reader/models/action.py
lif_reader/models/action_parameter.py
lif_reader/models/edge.py
lif_reader/models/layout.py
lif_reader/models/lif.py
lif_reader/models/load_restriction.py
lif_reader/models/metaInformation.py
lif_reader/models/node.py
lif_reader/models/station.py
lif_reader/models/trajectory.py
lif_reader/models/vehicle_properties.py
lif_reader/utils/__init__.py
lif_reader/utils/config_loader.py
lif_reader/utils/exceptions.py
lif_reader/utils/utils.py
lif_reader/utils/validators/__init__.py
lif_reader/utils/validators/lif_validator.py
lif_reader/utils/validators/vda5050_validator.py
lif_reader/vda5050/__init__.py
lif_reader/vda5050/communication.py
lif_reader/vda5050/message_handler.py
lif_reader/vda5050/models.py
tests/__init__.py
tests/test_graph_renderer.py
tests/test_json_reader.py
tests/test_lif_graph.py
tests/test_models.py
tests/test_vda5050_communication.py
lifreader-1.0.0.dist-info/LICENSE
lifreader-1.0.0.dist-info/METADATA
lifreader-1.0.0.dist-info/WHEEL
lifreader-1.0.0.dist-info/entry_points.txt
lifreader-1.0.0.dist-info/top_level.txt
lifreader-1.0.0.dist-info/RECORD
