Metadata-Version: 2.2
Name: LIFReader
Version: 1.0.0
Summary: A tool for parsing and visualizing AGV layouts from LIF files.
Home-page: https://github.com/DadaNanjesha/LIFReader
Author: Dada Nanjesha
Classifier: Programming Language :: Python :: 3
Classifier: License :: OSI Approved :: MIT License
Classifier: Operating System :: OS Independent
Requires-Python: >=3.7
License-File: LICENSE
Requires-Dist: networkx
Requires-Dist: matplotlib
Requires-Dist: pydantic
Dynamic: author
Dynamic: classifier
Dynamic: description
Dynamic: description-content-type
Dynamic: home-page
Dynamic: requires-dist
Dynamic: requires-python
Dynamic: summary
